pysynic/__init__.py
pysynic/synthetic_data.py
pysynic-0.0.7.dist-info/LICENSE
pysynic-0.0.7.dist-info/WHEEL
pysynic-0.0.7.dist-info/METADATA
pysynic-0.0.7.dist-info/RECORD
