Metadata-Version: 2.1
Name: pysynic
Version: 0.0.7
Summary: Helps to generated synthetic data that can be used to test ML models etc
Author-email: "Phillip Henry, Christopher Monit" <londonjavaman@gmail.com>
Requires-Python: >=3.7
Classifier: Programming Language :: Python :: 3
Classifier: License :: OSI Approved :: Apache Software License
Classifier: Operating System :: OS Independent
Requires-Dist: pytest
Project-URL: Homepage, https://github.com/phillhenry/pysynic/
